predict_smiles.py
data/GABAA.csv
data/MACCS.csv
data/application_domain.xlsx
data/experimental_compounds.xlsx
data/gaba_MolecularProperties.csv
data/gaba_smi.csv
data/histogram.xlsx
data/phylogenetic_tree.xlsx
data/plant_MolecularProperties.csv
data/plant_family.nwk
data/plant_prediction.xlsx
data/plant_raw.xlsx
data/plant_smi.csv
data/plant_species_Asteraceae.nwk
data/plant_species_Cupressaceae.nwk
data/plant_species_Lamiaceae.nwk
data/plant_species_Lauraceae.nwk
data/plant_species_Pinaceae.nwk
data/processed_plant.xlsx
data_analysis/Figure 2.ipynb
"data_analysis/Figure 6, figure S9-S14.ipynb"
data_analysis/Figure S1.ipynb
data_analysis/Figure S15-S16.ipynb
data_analysis/MolecularProperties.ipynb
data_analysis/application_domain.ipynb
data_analysis/data_processing.ipynb
data_analysis/negative.png
data_analysis/plot_molecular_scaffold.ipynb
data_analysis/positive.png
data_analysis/smiles_from_name.ipynb
data_analysis/.ipynb_checkpoints/Figure 2-checkpoint.ipynb
"data_analysis/.ipynb_checkpoints/Figure 6, figure S9-S14-checkpoint.ipynb"
data_analysis/.ipynb_checkpoints/Figure S1-checkpoint.ipynb
data_analysis/.ipynb_checkpoints/Figure S15-S16-checkpoint.ipynb
data_analysis/.ipynb_checkpoints/MolecularProperties-checkpoint.ipynb
data_analysis/.ipynb_checkpoints/application_domain-checkpoint.ipynb
data_analysis/.ipynb_checkpoints/data_processing-checkpoint.ipynb
data_analysis/.ipynb_checkpoints/plot_molecular_scaffold-checkpoint.ipynb
data_analysis/.ipynb_checkpoints/smiles_from_name-checkpoint.ipynb
data_analysis/__pycache__/ScoConfig.cpython-37.pyc
data_analysis/qsar_ad/__init__.py
data_analysis/qsar_ad/_nbdev.py
data_analysis/qsar_ad/applicability_domain.py
data_analysis/qsar_ad/__pycache__/__init__.cpython-38.pyc
data_analysis/qsar_ad/__pycache__/__init__.cpython-39.pyc
data_analysis/qsar_ad/__pycache__/applicability_domain.cpython-38.pyc
data_analysis/qsar_ad/__pycache__/applicability_domain.cpython-39.pyc
models/Predict.ipynb
models/Train_Stacking.ipynb
sleep_model-0.1.1.dist-info/METADATA
sleep_model-0.1.1.dist-info/WHEEL
sleep_model-0.1.1.dist-info/entry_points.txt
sleep_model-0.1.1.dist-info/top_level.txt
sleep_model-0.1.1.dist-info/RECORD
