Metadata-Version: 2.1
Name: sleep_model
Version: 0.1.1
Summary: Your package description
Author: Peiqin Shi
Project-URL: Homepage, https://github.com/PeiqinShi/Sleep-model
Project-URL: Bug-Tracker, https://github.com/PeiqinShi/Sleep-model/issues
Classifier: Programming Language :: Python :: 3
Classifier: License :: OSI Approved :: MIT License
Classifier: Operating System :: OS Independent
Requires-Python: >=3.8
Requires-Dist: deepchem==2.7.1
Requires-Dist: pandas>=2.0.3
Requires-Dist: pubchempy==1.0.4
Requires-Dist: pycirclize==1.6.0
Requires-Dist: rdkit==2023.3.1
Requires-Dist: requests>=2.25.0
Requires-Dist: seaborn>=0.13.2
Requires-Dist: xgboost==1.7.6
Requires-Dist: scikit-learn==1.0.2
Requires-Dist: cryptography==45.0.7
